<drumkit_info><name>Ian Hall Combined Drum Kit</name><author>Clayton Corrello</author><info>Ian Hall Combined Autogenerated Kit</info><license>GPLv3</license><instrumentList><instrument><id>0</id><name>35kick</name><volume>1</volume><isMuted>false</isMuted><pan_L>1</pan_L><pan_R>1</pan_R><randomPitchFactor>0</randomPitchFactor><filterActive>false</filterActive><filterCutoff>1</filterCutoff><filterResonance>0</filterResonance><Attack>0</Attack><Decay>0</Decay><Sustain>1</Sustain><Release>1000</Release><exclude /><midiOutNote>60</midiOutNote><layer><filename>t_35kick.flac</filename><min>0</min><max>1</max><gain>1</gain><pitch>-12</pitch></layer></instrument><instrument><id>1</id><name>37rim_shot</name><volume>1</volume><isMuted>false</isMuted><pan_L>1</pan_L><pan_R>1</pan_R><randomPitchFactor>0</randomPitchFactor><filterActive>false</filterActive><filterCutoff>1</filterCutoff><filterResonance>0</filterResonance><Attack>0</Attack><Decay>0</Decay><Sustain>1</Sustain><Release>1000</Release><exclude /><midiOutNote>61</midiOutNote><layer><filename>t_37rim_shot.flac</filename><min>0</min><max>1</max><gain>1</gain><pitch>-12</pitch></layer></instrument><instrument><id>2</id><name>38snare</name><volume>1</volume><isMuted>false</isMuted><pan_L>1</pan_L><pan_R>1</pan_R><randomPitchFactor>0</randomPitchFactor><filterActive>false</filterActive><filterCutoff>1</filterCutoff><filterResonance>0</filterResonance><Attack>0</Attack><Decay>0</Decay><Sustain>1</Sustain><Release>1000</Release><exclude /><midiOutNote>62</midiOutNote><layer><filename>t_38snare.flac</filename><min>0</min><max>1</max><gain>1</gain><pitch>-12</pitch></layer></instrument><instrument><id>3</id><name>39snare_side_stick</name><volume>1</volume><isMuted>false</isMuted><pan_L>1</pan_L><pan_R>1</pan_R><randomPitchFactor>0</randomPitchFactor><filterActive>false</filterActive><filterCutoff>1</filterCutoff><filterResonance>0</filterResonance><Attack>0</Attack><Decay>0</Decay><Sustain>1</Sustain><Release>1000</Release><exclude /><midiOutNote>63</midiOutNote><layer><filename>t_39snare_side_stick.flac</filename><min>0</min><max>1</max><gain>1</gain><pitch>-12</pitch></layer></instrument><instrument><id>4</id><name>42hihat_closed</name><volume>1</volume><isMuted>false</isMuted><pan_L>1</pan_L><pan_R>1</pan_R><randomPitchFactor>0</randomPitchFactor><filterActive>false</filterActive><filterCutoff>1</filterCutoff><filterResonance>0</filterResonance><Attack>0</Attack><Decay>0</Decay><Sustain>1</Sustain><Release>1000</Release><exclude /><midiOutNote>64</midiOutNote><layer><filename>t_42hihat_closed.flac</filename><min>0</min><max>1</max><gain>1</gain><pitch>-12</pitch></layer></instrument><instrument><id>5</id><name>43floorTom</name><volume>1</volume><isMuted>false</isMuted><pan_L>1</pan_L><pan_R>1</pan_R><randomPitchFactor>0</randomPitchFactor><filterActive>false</filterActive><filterCutoff>1</filterCutoff><filterResonance>0</filterResonance><Attack>0</Attack><Decay>0</Decay><Sustain>1</Sustain><Release>1000</Release><exclude /><midiOutNote>65</midiOutNote><layer><filename>t_43floorTom.flac</filename><min>0</min><max>1</max><gain>1</gain><pitch>0</pitch></layer></instrument><instrument><id>6</id><name>44hihat_slushy</name><volume>1</volume><isMuted>false</isMuted><pan_L>1</pan_L><pan_R>1</pan_R><randomPitchFactor>0</randomPitchFactor><filterActive>false</filterActive><filterCutoff>1</filterCutoff><filterResonance>0</filterResonance><Attack>0</Attack><Decay>0</Decay><Sustain>1</Sustain><Release>1000</Release><exclude /><midiOutNote>66</midiOutNote><layer><filename>t_44hihat_slushy.flac</filename><min>0</min><max>1</max><gain>1</gain><pitch>0</pitch></layer></instrument><instrument><id>7</id><name>45rack_tom</name><volume>1</volume><isMuted>false</isMuted><pan_L>1</pan_L><pan_R>1</pan_R><randomPitchFactor>0</randomPitchFactor><filterActive>false</filterActive><filterCutoff>1</filterCutoff><filterResonance>0</filterResonance><Attack>0</Attack><Decay>0</Decay><Sustain>1</Sustain><Release>1000</Release><exclude /><midiOutNote>67</midiOutNote><layer><filename>t_45rack_tom.flac</filename><min>0</min><max>1</max><gain>1</gain><pitch>0</pitch></layer></instrument><instrument><id>8</id><name>46hihat_open</name><volume>1</volume><isMuted>false</isMuted><pan_L>1</pan_L><pan_R>1</pan_R><randomPitchFactor>0</randomPitchFactor><filterActive>false</filterActive><filterCutoff>1</filterCutoff><filterResonance>0</filterResonance><Attack>0</Attack><Decay>0</Decay><Sustain>1</Sustain><Release>1000</Release><exclude /><midiOutNote>68</midiOutNote><layer><filename>t_46hihat_open.flac</filename><min>0</min><max>1</max><gain>1</gain><pitch>8</pitch></layer></instrument><instrument><id>9</id><name>49crash</name><volume>1</volume><isMuted>false</isMuted><pan_L>1</pan_L><pan_R>1</pan_R><randomPitchFactor>0</randomPitchFactor><filterActive>false</filterActive><filterCutoff>1</filterCutoff><filterResonance>0</filterResonance><Attack>0</Attack><Decay>0</Decay><Sustain>1</Sustain><Release>1000</Release><exclude /><midiOutNote>69</midiOutNote><layer><filename>t_49crash.flac</filename><min>0</min><max>1</max><gain>1</gain><pitch>8</pitch></layer></instrument><instrument><id>10</id><name>51ride</name><volume>1</volume><isMuted>false</isMuted><pan_L>1</pan_L><pan_R>1</pan_R><randomPitchFactor>0</randomPitchFactor><filterActive>false</filterActive><filterCutoff>1</filterCutoff><filterResonance>0</filterResonance><Attack>0</Attack><Decay>0</Decay><Sustain>1</Sustain><Release>1000</Release><exclude /><midiOutNote>70</midiOutNote><layer><filename>t_51ride.flac</filename><min>0</min><max>1</max><gain>1</gain><pitch>8</pitch></layer></instrument><instrument><id>11</id><name>52chinese_cymbal</name><volume>1</volume><isMuted>false</isMuted><pan_L>1</pan_L><pan_R>1</pan_R><randomPitchFactor>0</randomPitchFactor><filterActive>false</filterActive><filterCutoff>1</filterCutoff><filterResonance>0</filterResonance><Attack>0</Attack><Decay>0</Decay><Sustain>1</Sustain><Release>1000</Release><exclude /><midiOutNote>71</midiOutNote><layer><filename>t_52chinese_cymbal.flac</filename><min>0</min><max>1</max><gain>1</gain><pitch>8</pitch></layer></instrument><instrument><id>12</id><name>55splash</name><volume>1</volume><isMuted>false</isMuted><pan_L>1</pan_L><pan_R>1</pan_R><randomPitchFactor>0</randomPitchFactor><filterActive>false</filterActive><filterCutoff>1</filterCutoff><filterResonance>0</filterResonance><Attack>0</Attack><Decay>0</Decay><Sustain>1</Sustain><Release>1000</Release><exclude /><midiOutNote>72</midiOutNote><layer><filename>t_55splash.flac</filename><min>0</min><max>1</max><gain>1</gain><pitch>8</pitch></layer></instrument></instrumentList></drumkit_info>